{
  "cards": [
      {
    "id": 1,
    "name": "Sports",
    "image_url": "assets/images/sports.jpg"
}, {
    "id": 2,
    "name": "Abstract",
    "image_url": "assets/images/abstract.jpg"
}, {
    "id": 3,
    "name": "Animals",
    "image_url": "assets/images/animals.jpg"
}, {
    "id": 4,
    "name": "Business",
    "image_url": "assets/images/business.jpg"
}, {
    "id": 5,
    "name": "Cats",
    "image_url": "assets/images/cats.jpg"
}, {
    "id": 6,
    "name": "Nightlife",
    "image_url": "assets/images/nightlife.jpg"
}, {
    "id": 7,
    "name": "Fashion",
    "image_url": "assets/images/fashion.jpg"
}, {
    "id": 8,
    "name": "Food",
    "image_url": "assets/images/food.jpg"
}, {
    "id": 9,
    "name": "Nature",
    "image_url": "assets/images/nature.jpg"
}, {
    "id": 10,
    "name": "People",
    "image_url": "assets/images/people.jpg"
}
  ]
}